pyusermanager/__init__.py
pyusermanager/_version.py
pyusermanager/auth_type_enum.py
pyusermanager/authprovider_class.py
pyusermanager/custom_exceptions.py
pyusermanager/data_classes.py
pyusermanager/ldap_stuff.py
pyusermanager/login_class.py
pyusermanager/perms_class.py
pyusermanager/user_funcs.py
pyusermanager/Config/__init__.py
pyusermanager/Config/config_ad_class.py
pyusermanager/Config/config_base_class.py
pyusermanager/Config/config_general_class.py
pyusermanager/Config/db_providers/__init__.py
pyusermanager/Config/db_providers/prov_base.py
pyusermanager/Config/db_providers/prov_cockroachdb.py
pyusermanager/Config/db_providers/prov_mysql.py
pyusermanager/Config/db_providers/prov_oracle.py
pyusermanager/Config/db_providers/prov_postgresql.py
pyusermanager/Config/db_providers/prov_sqlite.py
pyusermanager/Token/__init__.py
pyusermanager/Token/token_activation_class.py
pyusermanager/Token/token_auth_class.py
pyusermanager/Token/token_base_class.py
pyusermanager/Token/token_reset_class.py
pyusermanager-2.0.10.dist-info/LICENSE
pyusermanager-2.0.10.dist-info/METADATA
pyusermanager-2.0.10.dist-info/WHEEL
pyusermanager-2.0.10.dist-info/top_level.txt
pyusermanager-2.0.10.dist-info/RECORD
