Metadata-Version: 2.1
Name: pyusermanager
Version: 2.0.10
Summary: Some Functions to manage a User Database and do stuff with it!
Home-page: https://github.com/Aurvandill/pyusermanager
Author: Ole Hannemann
Author-email: cerberus885@gmail.com
License: MIT
Classifier: Programming Language :: Python :: 3.0
Classifier: Programming Language :: Python :: 3.9
Classifier: Development Status :: 5 - Production/Stable
Classifier: License :: OSI Approved :: MIT License
License-File: LICENSE
Requires-Dist: setuptools (>=45.0)
Requires-Dist: pony
Requires-Dist: python-ldap
Requires-Dist: bcrypt
